{
    "businesses": [
      {
        "name": "Timaru Yamaha",
        "address": "145 Hilton Highway, Washdyke, Timaru",
        "phonenumber": "03 688 7166",
        "website": "www.timaruyamaha.co.nz",
        "email": "info@timaruyamaha.co.nz",
        "imageurl": "https://jasnatbyui.github.io/wdd230/Chamber/images/Screenshot_TimaruYamaha.png"
      },
      {
        "name": "Timaru Chemist",
        "address": "14 Stafford St, Timaru",
        "phonenumber": "03 688 7946",
        "website": "www.timaruchemist.co.nz",
        "email": "info@timaruchemistco.nz",
        "imageurl": "https://jasnatbyui.github.io/wdd230/Chamber/images/Screenshot_TimaruChemist.png"
      },
      {
        "name": "Timaru Asian",
        "address": "100 Stafford Street, Timaru",
        "phonenumber": "03 678 7226",
        "website": "www.timaruasian.co.nz",
        "email": "info@timaruasian.co.nz",
        "imageurl": "https://jasnatbyui.github.io/wdd230/Chamber/images/Screenshot_TimaruAsian.png"
      },
      {
        "name": "Timaru Fish N Chips",
        "address": "202 Hilton Highway, Washdyke, Timaru",
        "phonenumber": "03 688 6746",
        "website": "www.timarufnc.co.nz",
        "email": "info@timarufnc.co.nz",
        "imageurl": "https://jasnatbyui.github.io/wdd230/Chamber/images/Screenshot_TimaruFnC.png"
      },
      {
        "name": "Timaru Movie Max",
        "address": "45 Stafford Street, Timaru",
        "phonenumber": "03 688 7544",
        "website": "www.moviemax.co.nz",
        "email": "info@moviemax.co.nz",
        "imageurl": "https://jasnatbyui.github.io/wdd230/Chamber/images/Screenshot_TimaruMovies.png"
      },
      {
        "name": "Timaru Security",
        "address": "5 Hilton Highway, Washdyke, Timaru",
        "phonenumber": "03 678 4466",
        "website": "www.timarusecurity.co.nz",
        "email": "info@timarusecurity.co.nz",
        "imageurl": "https://jasnatbyui.github.io/wdd230/Chamber/images/Screenshot_TimaruSecurity.png"
      },
      {
        "name": "Timaru Motors",
        "address": "33 Church Street, Timaru",
        "phonenumber": "03 688 1236",
        "website": "www.timarumotors.co.nz",
        "email": "info@timarumotors.co.nz",
        "imageurl": "https://jasnatbyui.github.io/wdd230/Chamber/images/Screenshot_TimaruMotors.png"
      },
      {
        "name": "Mackenzie and Willis Furniture",
        "address": ", Timaru",
        "phonenumber": "03 688 7166",
        "website": "www.mwfurniture.co.nz",
        "email": "info@mwfurniture.co.nz",
        "imageurl": "https://jasnatbyui.github.io/wdd230/Chamber/images/Screenshot_TimaruFurniture.png"
      },
      {
        "name": "Why Buy New",
        "address": "115 Stafford Street, Timaru",
        "phonenumber": "03 688 7166",
        "website": "www.whybuynew.co.nz",
        "email": "info@whybuynew.co.nz",
        "imageurl": "https://jasnatbyui.github.io/wdd230/Chamber/images/Screenshot_SecondHand.png"
      },
      {
        "name": "Barrett Kitchens",
        "address": "209 Seadown Road, Timaru",
        "phonenumber": "03 656 7177",
        "website": "www.barrettkitchens.co.nz",
        "email": "info@barrettkitchens.co.nz",
        "imageurl": "https://jasnatbyui.github.io/wdd230/Chamber/images/Screenshot_TimaruJoinery.png"
      },
      {
        "name": "Fashion Focus",
        "address": "45 King Street, Timaru",
        "phonenumber": "03 688 1166",
        "website": "www.fashionfocus.co.nz",
        "email": "info@fashionfocus.co.nz",
        "imageurl": "https://jasnatbyui.github.io/wdd230/Chamber/images/Screenshot_TimaruFashion.png"
      },
      {
        "name": "Bullock Bar and Restaurant",
        "address": "55 Evans Street, Timaru",
        "phonenumber": "03 688 7886",
        "website": "www.bullockbar.co.nz",
        "email": "info@bullockbar.co.nz",
        "imageurl": "https://jasnatbyui.github.io/wdd230/Chamber/images/Screenshot_TimaruRestaurant.png"
      }
    ]
}